kakaobot/__init__.py
kakaobot/kakaobot.py
kakaobot/types.py
python_kakaobot-0.0.2.dist-info/DESCRIPTION.rst
python_kakaobot-0.0.2.dist-info/METADATA
python_kakaobot-0.0.2.dist-info/RECORD
python_kakaobot-0.0.2.dist-info/WHEEL
python_kakaobot-0.0.2.dist-info/metadata.json
python_kakaobot-0.0.2.dist-info/top_level.txt
