Metadata-Version: 2.0
Name: python-kakaobot
Version: 0.0.2
Summary: Super simple framework for Kakaotalk auto-reply bot based on aiohttp
Home-page: https://github.com/hallazzang/kakaobot
Author: Hanjun Kim
Author-email: hallazzang@gmail.com
License: MIT
Platform: any
Classifier: Development Status :: 3 - Alpha
Classifier: Intended Audience :: Developers
Classifier: License :: OSI Approved :: MIT License
Classifier: Operating System :: OS Independent
Classifier: Programming Language :: Python
Classifier: Programming Language :: Python :: 3
Classifier: Programming Language :: Python :: 3 :: Only
Classifier: Programming Language :: Python :: 3.5
Classifier: Programming Language :: Python :: 3.6
Classifier: Topic :: Software Development :: Libraries :: Python Modules
Requires-Python: >=3.5
Requires-Dist: aiohttp (>=2.3.6)
